{
  "servers": [
    {
      "id": "lobby-mc3ilstt-p3afgpwv",
      "region": "Atlanta, Georgia",
      "gamemode": "survival",
      "players": [],
      "clans": [],
      "status": "FULL(No connectable)",
      "total_players": 0,
      "last_parsed": "2025-06-26T09:15:32.042618"
    },
    {
      "id": "lobby-mc3ils9y-40tdl6qs",
      "region": "Atlanta, Georgia",
      "gamemode": "survival",
      "players": [],
      "clans": [],
      "status": "FULL(No connectable)",
      "total_players": 0,
      "last_parsed": "2025-06-26T09:15:32.042650"
    },
    {
      "id": "lobby-mc3ilrn8-6kmv6nmm",
      "region": "Atlanta, Georgia",
      "gamemode": "survival",
      "players": [],
      "clans": [],
      "status": "FULL(No connectable)",
      "total_players": 0,
      "last_parsed": "2025-06-26T09:15:32.042668"
    },
    {
      "id": "lobby-mc3ilv4e-qkqixhoy",
      "region": "Frankfurt, Deutschland",
      "gamemode": "survival",
      "players": [],
      "clans": [],
      "status": "FULL(No connectable)",
      "total_players": 0,
      "last_parsed": "2025-06-26T09:15:32.042688"
    },
    {
      "id": "lobby-mc3ilukn-deva9p6o",
      "region": "Frankfurt, Deutschland",
      "gamemode": "survival",
      "players": [],
      "clans": [],
      "status": "FULL(No connectable)",
      "total_players": 0,
      "last_parsed": "2025-06-26T09:15:32.042702"
    },
    {
      "id": "lobby-mc3iltp3-udgl8jjk",
      "region": "Frankfurt, Deutschland",
      "gamemode": "survival",
      "players": [],
      "clans": [],
      "status": "FULL(No connectable)",
      "total_players": 0,
      "last_parsed": "2025-06-26T09:15:32.042715"
    },
    {
      "id": "lobby-mc3ilwax-ndie7fpg",
      "region": "Los Angeles, California",
      "gamemode": "survival",
      "players": [],
      "clans": [],
      "status": "FULL(No connectable)",
      "total_players": 0,
      "last_parsed": "2025-06-26T09:15:32.042729"
    },
    {
      "id": "lobby-mc3ilvou-mqyykcgd",
      "region": "Los Angeles, California",
      "gamemode": "survival",
      "players": [],
      "clans": [],
      "status": "FULL(No connectable)",
      "total_players": 0,
      "last_parsed": "2025-06-26T09:15:32.042745"
    },
    {
      "id": "lobby-mc3ilwuw-ijlqcwl3",
      "region": "Sydney, Australia",
      "gamemode": "survival",
      "players": [],
      "clans": [],
      "status": "FULL(No connectable)",
      "total_players": 0,
      "last_parsed": "2025-06-26T09:15:32.042760"
    },
    {
      "id": "lobby-mc3ilzpa-w23cwwwf",
      "region": "Osaka, Japan",
      "gamemode": "survival",
      "players": [],
      "clans": [],
      "status": "FULL(No connectable)",
      "total_players": 0,
      "last_parsed": "2025-06-26T09:15:32.042774"
    },
    {
      "id": "lobby-mc3ilyio-ua1yjwvr",
      "region": "Osaka, Japan",
      "gamemode": "survival",
      "players": [],
      "clans": [],
      "status": "FULL(No connectable)",
      "total_players": 0,
      "last_parsed": "2025-06-26T09:15:32.042787"
    },
    {
      "id": "lobby-mc3im0nf-va7zewbu",
      "region": "Atlanta, Georgia",
      "gamemode": "survival",
      "players": [],
      "clans": [],
      "status": "FULL(No connectable)",
      "total_players": 0,
      "last_parsed": "2025-06-26T09:15:32.042802"
    },
    {
      "id": "lobby-mc3im12d-pqpnpkuw",
      "region": "Frankfurt, Deutschland",
      "gamemode": "survival",
      "players": [],
      "clans": [],
      "status": "FULL(No connectable)",
      "total_players": 0,
      "last_parsed": "2025-06-26T09:15:33.366116"
    }
  ]
}