{
  "servers": [
    {
      "id": "lobby-mc3ilstt-p3afgpwv",
      "region": "Atlanta, Georgia",
      "gamemode": "survival",
      "players": [],
      "clans": [],
      "status": "FULL(No connectable)",
      "total_players": 0,
      "last_parsed": "2025-06-26T09:56:19.215284"
    },
    {
      "id": "lobby-mc3ils9y-40tdl6qs",
      "region": "Atlanta, Georgia",
      "gamemode": "survival",
      "players": [],
      "clans": [],
      "status": "FULL(No connectable)",
      "total_players": 0,
      "last_parsed": "2025-06-26T09:56:19.215327"
    },
    {
      "id": "lobby-mc3ilrn8-6kmv6nmm",
      "region": "Atlanta, Georgia",
      "gamemode": "survival",
      "players": [],
      "clans": [],
      "status": "FULL(No connectable)",
      "total_players": 0,
      "last_parsed": "2025-06-26T09:56:19.215349"
    },
    {
      "id": "lobby-mc3ilv4e-qkqixhoy",
      "region": "Frankfurt, Deutschland",
      "gamemode": "survival",
      "players": [],
      "clans": [],
      "status": "FULL(No connectable)",
      "total_players": 0,
      "last_parsed": "2025-06-26T09:56:19.215366"
    },
    {
      "id": "lobby-mc3ilukn-deva9p6o",
      "region": "Frankfurt, Deutschland",
      "gamemode": "survival",
      "players": [],
      "clans": [],
      "status": "FULL(No connectable)",
      "total_players": 0,
      "last_parsed": "2025-06-26T09:56:19.215381"
    },
    {
      "id": "lobby-mc3iltp3-udgl8jjk",
      "region": "Frankfurt, Deutschland",
      "gamemode": "survival",
      "players": [],
      "clans": [],
      "status": "FULL(No connectable)",
      "total_players": 0,
      "last_parsed": "2025-06-26T09:56:19.215397"
    },
    {
      "id": "lobby-mc3ilwax-ndie7fpg",
      "region": "Los Angeles, California",
      "gamemode": "survival",
      "players": [],
      "clans": [],
      "status": "FULL(No connectable)",
      "total_players": 0,
      "last_parsed": "2025-06-26T09:56:19.215412"
    },
    {
      "id": "lobby-mc3ilvou-mqyykcgd",
      "region": "Los Angeles, California",
      "gamemode": "survival",
      "players": [],
      "clans": [],
      "status": "FULL(No connectable)",
      "total_players": 0,
      "last_parsed": "2025-06-26T09:56:19.215427"
    },
    {
      "id": "lobby-mc3ilwuw-ijlqcwl3",
      "region": "Sydney, Australia",
      "gamemode": "survival",
      "players": [],
      "clans": [],
      "status": "FULL(No connectable)",
      "total_players": 0,
      "last_parsed": "2025-06-26T09:56:20.357538"
    },
    {
      "id": "lobby-mc3ilzpa-w23cwwwf",
      "region": "Osaka, Japan",
      "gamemode": "survival",
      "players": [],
      "clans": [],
      "status": "FULL(No connectable)",
      "total_players": 0,
      "last_parsed": "2025-06-26T09:56:20.357576"
    },
    {
      "id": "lobby-mc3ilyio-ua1yjwvr",
      "region": "Osaka, Japan",
      "gamemode": "survival",
      "players": [],
      "clans": [],
      "status": "FULL(No connectable)",
      "total_players": 0,
      "last_parsed": "2025-06-26T09:56:20.357591"
    },
    {
      "id": "lobby-mc3im0nf-va7zewbu",
      "region": "Atlanta, Georgia",
      "gamemode": "survival",
      "players": [],
      "clans": [],
      "status": "FULL(No connectable)",
      "total_players": 0,
      "last_parsed": "2025-06-26T09:56:20.357609"
    },
    {
      "id": "lobby-mc3im12d-pqpnpkuw",
      "region": "Frankfurt, Deutschland",
      "gamemode": "survival",
      "players": [],
      "clans": [],
      "status": "FULL(No connectable)",
      "total_players": 0,
      "last_parsed": "2025-06-26T09:56:20.357626"
    }
  ]
}