{
  "servers": [
    {
      "id": "lobby-mc3ilstt-p3afgpwv",
      "region": "Atlanta, Georgia",
      "gamemode": "survival",
      "players": [
        "Pancracio",
        "ExecOut",
        "muymuyencantador",
        "45",
        "Enes%E2%84%A2%2A",
        "GD",
        "n199er",
        "K%CE%B1%CA%85%D2%BD%CE%B9%C9%A0%D4%8B%CE%B1",
        "DevastMod%20Bot",
        "a%CC%B3l%CC%B3l%CC%B3o%CC%B3",
        "Jos%C3%A9%20LTX",
        "e%C3%A7ajapreparadapr",
        "ernesto",
        "x",
        "%EA%A7%81%E0%BC%92%E2%98%AC%F0%9D%93%A3%F0%9D%93%A2%F0%9D%93%9C%E2%98%AC%E0%BC%92%EA%A7%82",
        "%E2%AD%90",
        "Duvanproxz",
        "vnombres123",
        "Pasta%20Rica",
        "Nevernopanda",
        "AwesomedudeX",
        "unrandomjpg"
      ],
      "clans": [
        "DVN",
        "MERC",
        "D1",
        "777"
      ],
      "status": "Connected",
      "total_players": 22,
      "last_parsed": "2025-06-24T23:05:15.055528"
    },
    {
      "id": "lobby-mc3ils9y-40tdl6qs",
      "region": "Atlanta, Georgia",
      "gamemode": "survival",
      "players": [
        "DevastMod%20Bot(2 bots)",
        "sigma",
        "wassi",
        "OXY_GEN%F0%9F%90%B1%E2%80%8D%F0%9F%91%A4",
        "SWAT",
        "%E5%B0%88%E6%A5%AD%E6%9C%80%E5%A4%A7%20%E3%83%84%20%E2%82%B1%E2%B1%A4%C3%98%20%F0%9D%95%84%E2%82%B3%E4%B9%99"
      ],
      "clans": [
        "WA"
      ],
      "status": "Connected",
      "total_players": 7,
      "last_parsed": "2025-06-24T23:05:14.939898"
    },
    {
      "id": "lobby-mc3ilrn8-6kmv6nmm",
      "region": "Atlanta, Georgia",
      "gamemode": "survival",
      "players": [
        "4",
        "63",
        "DevastMod%20Bot(2 bots)",
        "%20%20"
      ],
      "clans": [],
      "status": "Connected",
      "total_players": 5,
      "last_parsed": "2025-06-24T23:05:15.099024"
    },
    {
      "id": "lobby-mc3ilv4e-qkqixhoy",
      "region": "Frankfurt, Deutschland",
      "gamemode": "survival",
      "players": [
        "%E4%B9%82%E4%B9%82%E4%B9%82%20(8 bots)",
        "%40F2%2932DANI4KA%2A%28",
        "%D0%BA%D1%82%D0%BE%20%D0%BF%D1%80%D0%BE%D1%87%D0%B5%D0%BB%20%D0%B3%D0%B5%D0%B9",
        "%D1%8F%20%D1%80%D1%83%D1%81%D1%81%D0%BA%D0%B8%D0%B9",
        "%E2%82%BF%C9%AA%E1%B4%9B%E1%B4%84%E1%B4%8F%C9%AA%C9%B4",
        "Xman",
        "DevastMod%20Bot(2 bots)",
        "Tuntematon",
        "test",
        "CTPAX%20BOMJEY",
        "%E3%80%90%E2%84%B3%F0%9D%93%90%F0%9D%90%8A%F0%9D%90%92%E3%80%91%E3%80%90%E1%A6%93%F0%9D%93%AC%CF%81%E3%80%91",
        "Im%20trash%20no%20kill",
        "%E2%81%BF%E1%B5%92%E1%B5%92%E1%B5%87%CB%A2%20%24%21Hl%21%24",
        "%E1%B5%89%E1%B5%9B%E2%81%B1%F0%9F%86%81%F0%9F%85%B4%F0%9F%85%B0%F0%9F%85%BB%C2%A5%E2%82%AE%E1%B5%88%E1%B5%87%CB%A2",
        "%E2%82%AD%C9%84%E2%B1%A7%E2%82%AE%E2%82%B3%E2%B1%A4%E2%82%B1%C5%82%E2%82%AD%20",
        "qerseur",
        "%E2%98%A0%20Rochdi%20%E2%87%8F%E2%84%A2%F0%9F%8F%B4%E2%80%8D%E2%98%A0",
        "S%CD%9B%E1%B4%9B%E2%B7%AEa%CD%A3nD%CD%A9r%CD%ACi%CD%A5%D1%80%E2%B7%AC%E2%B7%AC",
        "amil",
        "%D0%B1%D0%B0%D0%B1%D1%83%D0%B8%D0%BD%20%D1%81%20%D0%BA%D0%BE%D0%BF%D1%8C%D0%B5%D0%BC"
      ],
      "clans": [
        "SCP",
        "EVI",
        "RUSS",
        "DZZD",
        "ADS",
        "SD"
      ],
      "status": "Connected",
      "total_players": 28,
      "last_parsed": "2025-06-24T23:05:14.607768"
    },
    {
      "id": "lobby-mc3ilukn-deva9p6o",
      "region": "Frankfurt, Deutschland",
      "gamemode": "survival",
      "players": [
        "DevastMod%20Bot",
        "srost",
        "%EA%A7%81%F0%9D%95%BD%F0%9D%92%8A%F0%9D%93%92%C4%A6%F0%9D%93%90%F0%9D%95%BD%F0%9D%93%93%EA%A7%82",
        "%D0%BA%D0%B0%D0%BB%D0%BE%D0%B5%D0%B4"
      ],
      "clans": [
        "DWD",
        "DSDSD"
      ],
      "status": "Connected",
      "total_players": 4,
      "last_parsed": "2025-06-24T23:05:17.029992"
    },
    {
      "id": "lobby-mc3iltp3-udgl8jjk",
      "region": "Frankfurt, Deutschland",
      "gamemode": "survival",
      "players": [
        "%D1%85%D0%BE%D0%B3%20%D0%B4%D0%B2%D0%B0%20%D0%B8%20%D1%88%D0%B5%D1%81%D1%82%D1%8C",
        "Garnacho",
        "S1%20gg",
        "DevastMod%20Bot(2 bots)",
        "%E6%84%9B%F0%9D%95%8A%F0%9D%9F%8F%D0%BF%D0%B8%D0%B7%D0%B4%D0%BE%D1%85%D1%83%D1%8F%D0%BD%D1%8C",
        "%E2%99%96%E2%88%82%E2%82%AC%F0%9D%90%8C%E2%99%A2N%CC%BE%E2%99%A5%EF%BC%88%E9%9F%B3%E3%81%B2%E5%9B%B2%EF%BC%89",
        "%D0%BB%D1%8E%D0%BB%D1%8F%20%D0%BA%D0%B5%D0%B1%D0%B0%D0%B1",
        "%F0%9D%95%BD%F0%9D%96%8A%F0%9D%96%98%F0%9D%96%8A%F0%9D%95%BF",
        "%D0%BF%D0%B0%D1%80%D0%B0%D0%BB%D0%BB%D0%B5%D0%BB%D0%B5%D0%BF%D0%B8%D0%BF%D0%B5%D0%B4",
        "333333"
      ],
      "clans": [
        "SSSSS",
        "CHP",
        "DAMN"
      ],
      "status": "Connected",
      "total_players": 11,
      "last_parsed": "2025-06-24T23:05:14.678864"
    },
    {
      "id": "lobby-mc3ilwax-ndie7fpg",
      "region": "Los Angeles, California",
      "gamemode": "survival",
      "players": [
        "DevastMod%20Bot(2 bots)",
        "The%20guy",
        "BD2013",
        "NOON%20Angry%20",
        "craftynewt",
        "Player"
      ],
      "clans": [
        "TRIO"
      ],
      "status": "Connected",
      "total_players": 7,
      "last_parsed": "2025-06-24T23:05:15.116027"
    },
    {
      "id": "lobby-mc3ilvou-mqyykcgd",
      "region": "Los Angeles, California",
      "gamemode": "survival",
      "players": [
        "Saskid",
        "4",
        "Tr-tklyn",
        "DevastMod%20Bot(2 bots)"
      ],
      "clans": [],
      "status": "Connected",
      "total_players": 5,
      "last_parsed": "2025-06-24T23:05:15.114602"
    },
    {
      "id": "lobby-mc3ilwuw-ijlqcwl3",
      "region": "Sydney, Australia",
      "gamemode": "survival",
      "players": [
        "4",
        "DevastMod%20Bot"
      ],
      "clans": [],
      "status": "Connected",
      "total_players": 2,
      "last_parsed": "2025-06-24T23:05:16.166061"
    },
    {
      "id": "lobby-mc3ilzpa-w23cwwwf",
      "region": "Osaka, Japan",
      "gamemode": "survival",
      "players": [
        "DevastMod%20Bot(2 bots)"
      ],
      "clans": [],
      "status": "Connected",
      "total_players": 2,
      "last_parsed": "2025-06-24T23:05:15.657141"
    },
    {
      "id": "lobby-mc3ilyio-ua1yjwvr",
      "region": "Osaka, Japan",
      "gamemode": "survival",
      "players": [
        "DevastMod%20Bot(2 bots)"
      ],
      "clans": [],
      "status": "Connected",
      "total_players": 2,
      "last_parsed": "2025-06-24T23:05:15.952861"
    },
    {
      "id": "lobby-mc3im0nf-va7zewbu",
      "region": "Atlanta, Georgia",
      "gamemode": "survival",
      "players": [
        "%E3%83%83",
        "DevastMod%20Bot(2 bots)",
        "Ismokedurpack%5E_%5E"
      ],
      "clans": [
        "SMOKE"
      ],
      "status": "Connected",
      "total_players": 4,
      "last_parsed": "2025-06-24T23:05:14.892892"
    },
    {
      "id": "lobby-mc3im12d-pqpnpkuw",
      "region": "Frankfurt, Deutschland",
      "gamemode": "survival",
      "players": [
        "%E2%9C%9E%F0%9D%93%93%F0%9D%96%94%F0%9D%96%93%E2%9C%9E",
        "DevastMod%20Bot(2 bots)"
      ],
      "clans": [
        "DON"
      ],
      "status": "Connected",
      "total_players": 3,
      "last_parsed": "2025-06-24T23:05:14.665679"
    }
  ]
}