{
  "servers": [
    {
      "id": "lobby-mc3ilstt-p3afgpwv",
      "region": "Atlanta, Georgia",
      "gamemode": "survival",
      "players": [],
      "clans": [],
      "status": "FULL(No connectable)",
      "total_players": 0,
      "last_parsed": "2025-06-26T05:46:42.488599"
    },
    {
      "id": "lobby-mc3ils9y-40tdl6qs",
      "region": "Atlanta, Georgia",
      "gamemode": "survival",
      "players": [],
      "clans": [],
      "status": "FULL(No connectable)",
      "total_players": 0,
      "last_parsed": "2025-06-26T05:46:42.488634"
    },
    {
      "id": "lobby-mc3ilrn8-6kmv6nmm",
      "region": "Atlanta, Georgia",
      "gamemode": "survival",
      "players": [],
      "clans": [],
      "status": "FULL(No connectable)",
      "total_players": 0,
      "last_parsed": "2025-06-26T05:46:42.488653"
    },
    {
      "id": "lobby-mc3ilv4e-qkqixhoy",
      "region": "Frankfurt, Deutschland",
      "gamemode": "survival",
      "players": [],
      "clans": [],
      "status": "FULL(No connectable)",
      "total_players": 0,
      "last_parsed": "2025-06-26T05:46:42.488667"
    },
    {
      "id": "lobby-mc3ilukn-deva9p6o",
      "region": "Frankfurt, Deutschland",
      "gamemode": "survival",
      "players": [],
      "clans": [],
      "status": "FULL(No connectable)",
      "total_players": 0,
      "last_parsed": "2025-06-26T05:46:42.488690"
    },
    {
      "id": "lobby-mc3iltp3-udgl8jjk",
      "region": "Frankfurt, Deutschland",
      "gamemode": "survival",
      "players": [],
      "clans": [],
      "status": "FULL(No connectable)",
      "total_players": 0,
      "last_parsed": "2025-06-26T05:46:42.488705"
    },
    {
      "id": "lobby-mc3ilwax-ndie7fpg",
      "region": "Los Angeles, California",
      "gamemode": "survival",
      "players": [],
      "clans": [],
      "status": "FULL(No connectable)",
      "total_players": 0,
      "last_parsed": "2025-06-26T05:46:42.488718"
    },
    {
      "id": "lobby-mc3ilvou-mqyykcgd",
      "region": "Los Angeles, California",
      "gamemode": "survival",
      "players": [],
      "clans": [],
      "status": "FULL(No connectable)",
      "total_players": 0,
      "last_parsed": "2025-06-26T05:46:42.488733"
    },
    {
      "id": "lobby-mc3ilwuw-ijlqcwl3",
      "region": "Sydney, Australia",
      "gamemode": "survival",
      "players": [],
      "clans": [],
      "status": "FULL(No connectable)",
      "total_players": 0,
      "last_parsed": "2025-06-26T05:46:42.488747"
    },
    {
      "id": "lobby-mc3ilzpa-w23cwwwf",
      "region": "Osaka, Japan",
      "gamemode": "survival",
      "players": [],
      "clans": [],
      "status": "FULL(No connectable)",
      "total_players": 0,
      "last_parsed": "2025-06-26T05:46:42.488763"
    },
    {
      "id": "lobby-mc3ilyio-ua1yjwvr",
      "region": "Osaka, Japan",
      "gamemode": "survival",
      "players": [],
      "clans": [],
      "status": "FULL(No connectable)",
      "total_players": 0,
      "last_parsed": "2025-06-26T05:46:42.488776"
    },
    {
      "id": "lobby-mc3im0nf-va7zewbu",
      "region": "Atlanta, Georgia",
      "gamemode": "survival",
      "players": [],
      "clans": [],
      "status": "FULL(No connectable)",
      "total_players": 0,
      "last_parsed": "2025-06-26T05:46:42.488791"
    },
    {
      "id": "lobby-mc3im12d-pqpnpkuw",
      "region": "Frankfurt, Deutschland",
      "gamemode": "survival",
      "players": [],
      "clans": [],
      "status": "FULL(No connectable)",
      "total_players": 0,
      "last_parsed": "2025-06-26T05:46:42.488806"
    }
  ]
}